MANIFEST.in
README.rst
setup.py
examples/data/pheno
examples/data/plink.bed
examples/data/plink.bim
examples/data/plink.fam
examples/gmat/cal_agmat.py
examples/gmat/cal_dgmat.py
examples/longwas/balance_test.py
examples/longwas/phe.balance.txt
examples/longwas/phe.unbalance.txt
examples/longwas/plink.bed
examples/longwas/plink.bim
examples/longwas/plink.fam
examples/longwas/setuptools.sh
examples/longwas/unbalance_test.py
examples/remma/remma_cpu.py
gmax/__init__.py
gmax.egg-info/PKG-INFO
gmax.egg-info/SOURCES.txt
gmax.egg-info/dependency_links.txt
gmax.egg-info/requires.txt
gmax.egg-info/top_level.txt
gmax/bayes/__init__.py
gmax/common/__init__.py
gmax/common/common.py
gmax/gmat/__init__.py
gmax/gmat/cal_gmat.py
gmax/longwas/__init__.py
gmax/longwas/common.py
gmax/longwas/balance/__init__.py
gmax/longwas/unbalance/__init__.py
gmax/longwas/unbalance/unbalance_emai.py
gmax/longwas/unbalance/unbalance_iter_mat.py
gmax/longwas/unbalance/unbalance_pre_mat.py
gmax/longwas/unbalance/unbalance_predata.py
gmax/longwas/unbalance/unbalance_varcom.py
gmax/mdlearn/__init__.py
gmax/mvlmm/__init__.py
gmax/pedigree/__init__.py
gmax/pedigree/process_pedigree.py
gmax/process_plink/__init__.py
gmax/process_plink/_build.py
gmax/process_plink/_read_plink_bed.c
gmax/process_plink/process_plink.py
gmax/process_plink/read_plink_bed.py
gmax/remma/__init__.py
gmax/remma/annotation.py
gmax/remma/pre_matrix.py
gmax/remma/random_pair.py
gmax/remma/remma_cpu/__init__.py
gmax/remma/remma_cpu/_build.py
gmax/remma/remma_cpu/_remma_epi_eff_cpu.c
gmax/remma/remma_cpu/remma_add_cpu.py
gmax/remma/remma_cpu/remma_dom_cpu.py
gmax/remma/remma_cpu/remma_epiAA_cpu.py
gmax/remma/remma_cpu/remma_epiAD_cpu.py
gmax/remma/remma_cpu/remma_epiDD_cpu.py
gmax/remma/remma_gpu/__init__.py
gmax/remma/remma_gpu/remma_epiAA_gpu.py
gmax/uvlmm/__init__.py
gmax/uvlmm/uvlmm_gwas.py
gmax/uvlmm/uvlmm_varcom.py
gmax/uvlmm/uvlmm_varcom_eigen.py