Metadata-Version: 1.0
Name: gmax
Version: 2020.1.7
Summary: Genomic Multivariate Analysis eXpedited
Home-page: https://github.com/chaoning/GMAX
Author: Chao Ning
Author-email: ningchao91@gmail.com
License: BSD License
Platform: all
